accelbyte_py_sdk/api/inventory/__init__.py
accelbyte_py_sdk/api/inventory/errors.py
accelbyte_py_sdk/api/inventory/models/__init__.py
accelbyte_py_sdk/api/inventory/models/apimodels_admin_update_item_req.py
accelbyte_py_sdk/api/inventory/models/apimodels_bulk_save_item_error.py
accelbyte_py_sdk/api/inventory/models/apimodels_bulk_save_item_resp.py
accelbyte_py_sdk/api/inventory/models/apimodels_chaining_operation_req.py
accelbyte_py_sdk/api/inventory/models/apimodels_chaining_operation_resp.py
accelbyte_py_sdk/api/inventory/models/apimodels_consume_item.py
accelbyte_py_sdk/api/inventory/models/apimodels_consume_item_req.py
accelbyte_py_sdk/api/inventory/models/apimodels_create_integration_configuration_req.py
accelbyte_py_sdk/api/inventory/models/apimodels_create_inventory_configuration_req.py
accelbyte_py_sdk/api/inventory/models/apimodels_create_inventory_req.py
accelbyte_py_sdk/api/inventory/models/apimodels_create_item.py
accelbyte_py_sdk/api/inventory/models/apimodels_create_item_type_req.py
accelbyte_py_sdk/api/inventory/models/apimodels_create_item_type_resp.py
accelbyte_py_sdk/api/inventory/models/apimodels_create_tag_req.py
accelbyte_py_sdk/api/inventory/models/apimodels_create_tag_resp.py
accelbyte_py_sdk/api/inventory/models/apimodels_delete_inventory_req.py
accelbyte_py_sdk/api/inventory/models/apimodels_error_response.py
accelbyte_py_sdk/api/inventory/models/apimodels_integration_configuration_resp.py
accelbyte_py_sdk/api/inventory/models/apimodels_inventory_config.py
accelbyte_py_sdk/api/inventory/models/apimodels_inventory_configuration_req.py
accelbyte_py_sdk/api/inventory/models/apimodels_inventory_configuration_resp.py
accelbyte_py_sdk/api/inventory/models/apimodels_inventory_resp.py
accelbyte_py_sdk/api/inventory/models/apimodels_item_resp.py
accelbyte_py_sdk/api/inventory/models/apimodels_list_integration_configurations_resp.py
accelbyte_py_sdk/api/inventory/models/apimodels_list_inventory_configurations_resp.py
accelbyte_py_sdk_service_inventory-0.20.0.dist-info/METADATA
accelbyte_py_sdk_service_inventory-0.20.0.dist-info/WHEEL
accelbyte_py_sdk_service_inventory-0.20.0.dist-info/top_level.txt
accelbyte_py_sdk_service_inventory-0.20.0.dist-info/RECORD
